{
  "name": "gutocarvalho-jenkins",
  "version": "1.0.0",
  "author": "gutocarvalho",
  "summary": "This module will install the latest jenkins v2",
  "license": "Apache-2.0",
  "source": "https://github.com/gutocarvalho/puppet-jenkins",
  "project_page": "https://github.com/gutocarvalho/puppet-jenkins",
  "issues_url": "https://github.com/gutocarvalho/puppet-jenkins/issues",
  "dependencies": [
    {
      "name": "puppetlabs/stdlib"
    },
    {
      "name": "puppetlabs/java"
    },
    {
      "name": "puppet/archive"
    }
  ],
  "data_provider": null,
  "operatingsystem_support": [
    {
      "operatingsystem": "CentOS",
      "operatingsystemrelease": [
        "6",
        "7"
      ]
    },
    {
      "operatingsystem": "OracleLinux",
      "operatingsystemrelease": [
        "6",
        "7"
      ]
    },
    {
      "operatingsystem": "RedHat",
      "operatingsystemrelease": [
        "6",
        "7"
      ]
    },
    {
      "operatingsystem": "Scientific",
      "operatingsystemrelease": [
        "6",
        "7"
      ]
    }
  ],
  "requirements": [
    {
      "name": "puppet",
      "version_requirement": ">= 4.10.0 < 6.0.0"
    }
  ],
  "pdk-version": "1.2.1",
  "template-url": "https://github.com/puppetlabs/pdk-module-template",
  "template-ref": "heads/master-0-g00b18a7"
}
